sunweg/__init__.py
sunweg/api.py
sunweg/const.py
sunweg/device.py
sunweg/plant.py
sunweg/util.py
sunweg-3.1.0.dist-info/LICENSE
sunweg-3.1.0.dist-info/METADATA
sunweg-3.1.0.dist-info/WHEEL
sunweg-3.1.0.dist-info/top_level.txt
sunweg-3.1.0.dist-info/RECORD
