Metadata-Version: 2.1
Name: sunweg
Version: 3.1.0
Summary: A library to retrieve data from sunweg.net
Home-page: https://github.com/rokam/sunweg
Author: rokam
Author-email: lucas@mindello.com.br
License: MIT
Classifier: Programming Language :: Python :: 3
Classifier: License :: OSI Approved :: MIT License
Classifier: Operating System :: OS Independent
Requires-Python: >=3.10
License-File: LICENSE
Requires-Dist: python-dateutil
Requires-Dist: requests
